iplib.py
iplib-1.2.1.data/scripts/cidrinfo
iplib-1.2.1.data/scripts/ipconv
iplib-1.2.1.data/scripts/nmconv
iplib-1.2.1.dist-info/METADATA
iplib-1.2.1.dist-info/RECORD
iplib-1.2.1.dist-info/WHEEL
iplib-1.2.1.dist-info/top_level.txt
